sxstools/__init__.py
sxstools/alignment.py
sxstools/coordinate_transform.py
sxstools/coordinate_transform_interp.py
sxstools/data_loader.py
sxstools/quantities.py
sxstools/rotations.py
sxstools/transforms.py
sxstools/waveformtools.code-workspace
sxstools-2025.7.15.dist-info/METADATA
sxstools-2025.7.15.dist-info/WHEEL
sxstools-2025.7.15.dist-info/licenses/LICENSE
sxstools-2025.7.15.dist-info/RECORD
