Metadata-Version: 2.4
Name: sxstools
Version: 2025.7.15
Summary:  Tools to handle sxs NR data 
Project-URL: Homepage, https://github.com/vaishakp/sxstools
Project-URL: Bug Tracker, https://github.com/vaishakp/sxstools/issues
Author-email: Vaishak Prasad <vaishakprasad@gmail.com>
License-File: LICENSE
Classifier: License :: OSI Approved :: MIT License
Classifier: Operating System :: OS Independent
Classifier: Programming Language :: Python :: 3
Requires-Python: >=3.11
Requires-Dist: scri
Requires-Dist: waveformtools
